{
  "files" : [

  ],
  "covers" : [
    {
      "desc" : "Understand how to use logarithms",
      "id" : "logarithms",
      "references" : [
        "https://en.wikipedia.org/wiki/Logarithm"
      ],
      "videos" : [
        "https://youtu.be/kqVpPSzkTYA?si=PSK_N1mGHGA6qhX2",
        "https://youtu.be/zzu2POfYv0Y?si=MPvGwTgF1DQjVbi2",
        "https://youtu.be/mQTWzLpCcW0?si=-VMNEuRoI2-nCZXE"
      ]
    },
    {
      "desc" : "Understand how to use logarithm properties",
      "id" : "log_properties",
      "references" : [
        "https://en.wikipedia.org/wiki/Logarithm#Logarithmic_identities"
      ],
      "videos" : [
        "https://youtu.be/Jtv9Lnf7Zw8?si=Em29zy7oT8ezCYz4"
      ]
    },
    {
      "references" : [
        "https://en.wikipedia.org/wiki/Natural_logarithm"
      ],
      "desc" : "Understand natural logs",
      "videos" : [
        "https://youtu.be/daUlTsnCNRQ?si=0WQE6BY59bRnm-k3"
      ],
      "id" : "log_natural"
    }
  ],
  "requires" : [
    "exponents",
    "exponent_properties",
    "python_basics",
    "spreadsheet"
  ]
}