{
  "kont_intro": {
    "desc": "Introduction to Kontinua",
    "chap_id": "introduction"
  },
  "chem_reaction": {
    "desc": "Intro to chemical reactions",
    "chap_id": "matter_energy_intro"
  },
  "atom": {
    "desc": "Able to define atom and a molecule",
    "chap_id": "matter_energy_intro"
  },
  "fma": {
    "desc": "The relationship between force, mass, and acceleration",
    "chap_id": "newtons_second_law"
  },
  "grav": {
    "desc": "Basic rules of gravity",
    "chap_id": "matter_energy_intro"
  },
  "periodic_tbl": {
    "desc": "Introduction to the Periodic Table",
    "chap_id": "matter_energy_intro"
  },
  "lewis_dot": {
    "desc": "Able to create of the Lewis Dot Structure models.",
    "chap_id": "matter_energy_intro"
  },
  "bonds": {
    "desc": "Define polar, non-polar, and covalent bonds.",
    "chap_id": "matter_energy_intro"
  },
  "conservation_law": {
    "desc": "Law of Conservation of Mass",
    "chap_id": "matter_energy_intro"
  },
  "mass_eng_equiv": {
    "desc": "E=mc^2 equation",
    "chap_id": "matter_energy_intro"
  },
  "molecules": {
    "desc": "be able to define a molecule",
    "chap_id": "matter_energy_intro"
  },
  "compounds": {
    "desc": "Identify compounds",
    "chap_id": "matter_energy_intro"
  },
  "consv_mass": {
    "desc": "Law of Conservation of Mass",
    "chap_id": "conservation_mass_energy"
  },
  "consv_energy": {
    "desc": "Conservation of Energy",
    "chap_id": "conservation_mass_energy"
  },
  "friction_intro": {
    "desc": "Define the basics of Friction",
    "chap_id": "conservation_mass_energy"
  },
  "systems": {
    "desc": "Able to define a system, open/closed systems, and isolated systems",
    "chap_id": "conservation_mass_energy"
  },
  "eq_chem_reaction": {
    "desc": "Able to balance chemical reactions",
    "chap_id": "conservation_mass_energy"
  },
  "acc": {
    "desc": "Able to calculate and define acceleration",
    "chap_id": "newtons_second_law"
  },
  "force": {
    "desc": "Able to calculate and define force",
    "chap_id": "newtons_second_law"
  },
  "newton_meters": {
    "desc": "Relationship between Newtons, newton meters, and joules",
    "chap_id": "newtons_second_law"
  },
  "energy-forms": {
    "desc": "An overview of different forms of energy",
    "chap_id": "work_energy"
  },
  "work": {
    "desc": "Define work as the process of a change in energy and calculate its units relative to energy",
    "chap_id": "work_energy"
  },
  "heat": {
    "desc": "Define heat energy",
    "chap_id": "work_energy"
  },
  "chem_energy": {
    "desc": "Intro to chemical energy and calories. Relates to chem_reations",
    "chap_id": "work_energy"
  },
  "electric_energy": {
    "desc": "Intro to Electricity",
    "chap_id": "work_energy"
  },
  "kinetic_energy": {
    "desc": "Able to define and use the formula to calculate kinetic energy of some object",
    "chap_id": "work_energy"
  },
  "grav_pot_energy": {
    "desc": "Able to calculate and define gravitation potential energy, specifically on earth",
    "chap_id": "work_energy"
  },
  "conservation_energy": {
    "desc": "the amount of energy is constant, just changes forms",
    "chap_id": "work_energy"
  },
  "efficiency": {
    "desc": "Define efficiency",
    "chap_id": "work_energy"
  },
  "work_energy_theorem": {
    "desc": "Able to relate work and energy",
    "chap_id": "work_energy"
  },
  "atomic-mass": {
    "desc": "Define atomic mass",
    "chap_id": "atomic_mass"
  },
  "atomic-weight": {
    "desc": "Define atomic weight (average mass of all atoms of that element)",
    "chap_id": "atomic_mass"
  },
  "mass-number": {
    "desc": "Define mass number in units (amu)",
    "chap_id": "atomic_mass"
  },
  "mole": {
    "desc": "Define a mole",
    "chap_id": "atomic_mass"
  },
  "read-periodic": {
    "desc": "Be able to read the basic facts from a periodic table",
    "chap_id": "atomic_mass"
  },
  "iso": {
    "desc": "Define isotopes",
    "chap_id": "atomic_mass"
  },
  "atomic-number": {
    "desc": "Define atomic number, importance in isotopes, and locate it on an element on the periodic table",
    "chap_id": "atomic_mass"
  },
  "chemical-symbols": {
    "desc": "Be able to write simple chemical symbols.",
    "chap_id": "atomic_mass"
  },
  "endo": {
    "desc": "Define an endothermic reaction",
    "chap_id": "chemical_reactions"
  },
  "exo": {
    "desc": "Define an exothermic reaction",
    "chap_id": "chemical_reactions"
  },
  "conv_fac": {
    "desc": "Conversion factors",
    "chap_id": "units_conversions"
  },
  "metric_pre": {
    "desc": "Prefixes of the metric system",
    "chap_id": "units_conversions"
  },
  "unit_types": {
    "desc": "Types of common units",
    "chap_id": "units_conversions"
  },
  "sim-mach": {
    "desc": "Basics of simple machines",
    "chap_id": "simple_machines"
  },
  "levers": {
    "desc": "Principles of levers",
    "chap_id": "simple_machines"
  },
  "inc-planes": {
    "desc": "Principles of inclined planes",
    "chap_id": "simple_machines"
  },
  "gears": {
    "desc": "Principles of gears",
    "chap_id": "simple_machines"
  },
  "hydraulics": {
    "desc": "Principles of hydraulics",
    "chap_id": "simple_machines"
  },
  "torque": {
    "desc": "Basics of Torque",
    "chap_id": "simple_machines"
  },
  "buoyancy": {
    "desc": "Principles of buoyancy",
    "chap_id": "buoyancy"
  },
  "density": {
    "desc": "Intro to density",
    "chap_id": "buoyancy"
  },
  "energy_heat_trans": {
    "desc": "Understand how much energy is used in a heat transfer, and what factors it depends on",
    "chap_id": "heat"
  },
  "thermal_eq": {
    "desc": "Define Thermal Equalibrium",
    "chap_id": "heat"
  },
  "heat_capacity": {
    "desc": "Define heat capacity",
    "chap_id": "heat"
  },
  "biases": {
    "desc": "Understand types and influences of biases",
    "chap_id": "biases1"
  },
  "normal_force": {
    "desc": "Define the normal force",
    "chap_id": "friction"
  },
  "static_friction": {
    "desc": "Define static friction",
    "chap_id": "friction"
  },
  "kinetic_friction": {
    "desc": "Define Kinetic Friction",
    "chap_id": "friction"
  },
  "greek-alpha": {
    "desc": "Understand and notetate basic greek letters in capital and lowercase",
    "chap_id": "greek"
  },
  "stats_sample": {
    "desc": "Identify what a sample is in statistics",
    "chap_id": "basic_statistics"
  },
  "stats_mean": {
    "desc": "Define what a mean is in statistics",
    "chap_id": "basic_statistics"
  },
  "stats-variance": {
    "desc": "Define variance in statistics",
    "chap_id": "basic_statistics"
  },
  "stats-std-dev": {
    "desc": "Define standard deviation in statistics",
    "chap_id": "basic_statistics"
  },
  "stats-outlier": {
    "desc": "Define Outlier",
    "chap_id": "basic_statistics"
  },
  "stats-median": {
    "desc": "Define Median",
    "chap_id": "basic_statistics"
  },
  "stats-histogram": {
    "desc": "Construct a histogram based on a set of date",
    "chap_id": "basic_statistics"
  },
  "stats-rms": {
    "desc": "Calculate root-mean squared",
    "chap_id": "basic_statistics"
  },
  "stats-mode": {
    "desc": "Define Modes",
    "chap_id": "basic_statistics"
  },
  "stats-bell-curve": {
    "desc": "Define Bell Curve",
    "chap_id": "basic_statistics"
  },
  "csv": {
    "desc": "Understand a csv file",
    "chap_id": "stat_spreadsheets"
  },
  "spreadsheet": {
    "desc": "Define a spreadsheet",
    "chap_id": "stat_spreadsheets"
  },
  "insulator": {
    "desc": "Understand what an insulator is",
    "chap_id": "dc1"
  },
  "conductor": {
    "desc": "Understand what a conductor is",
    "chap_id": "dc1"
  },
  "coulomb_amps": {
    "desc": "Understand the connection between coulumbs and amps",
    "chap_id": "dc1"
  },
  "open_circuit": {
    "desc": "Define an open circuit",
    "chap_id": "dc1"
  },
  "closed_circuit": {
    "desc": "Define a closed circuit",
    "chap_id": "dc1"
  },
  "resistance": {
    "desc": "Define Resistance",
    "chap_id": "dc1"
  },
  "volts": {
    "desc": "Define Voltage",
    "chap_id": "dc1"
  },
  "dc": {
    "desc": "Define the basics of a direct current",
    "chap_id": "dc1"
  },
  "watts": {
    "desc": "Define watts, note other equivalent units",
    "chap_id": "dc1"
  },
  "law_ohm": {
    "desc": "Define Ohm's law",
    "chap_id": "dc1"
  },
  "resistors-series": {
    "desc": "Define what it means for components to be in series",
    "chap_id": "dc_circuits"
  },
  "law-kirchhoff": {
    "desc": "Understand Kirchhoff's Voltage and Current Laws",
    "chap_id": "dc_circuits"
  },
  "resistors-parallel": {
    "desc": "Define what it means for components to be in parallel",
    "chap_id": "dc_circuits"
  },
  "charge": {
    "desc": "Be able to define and understand the concept of charge",
    "chap_id": "charge"
  },
  "law-coulomb": {
    "desc": "Define and use Coulomb's law",
    "chap_id": "charge"
  },
  "fertilizer": {
    "desc": "Understand how fertilizer works and grows plants",
    "chap_id": "fertilizer"
  },
  "haber-bosch": {
    "desc": "Understand the Haber-Bosch Process",
    "chap_id": "fertilizer"
  },
  "concrete": {
    "desc": "Understand the process of concrete development",
    "chap_id": "concrete"
  },
  "metals": {
    "desc": "Define and understand a metal in depth",
    "chap_id": "metals"
  },
  "alloy": {
    "desc": "Define an alloy",
    "chap_id": "metals"
  },
  "angle": {
    "desc": "Define and understand what angles are",
    "chap_id": "angles"
  },
  "degrees": {
    "desc": "Understand the unit degrees",
    "chap_id": "angles"
  },
  "rad": {
    "desc": "Understand the unit radians and convert to degrees",
    "chap_id": "angles"
  },
  "types-angle": {
    "desc": "Define obtuse, acute, supplementary, and complementary angles",
    "chap_id": "angles"
  },
  "triangle": {
    "desc": "Understand the properties of a triangle",
    "chap_id": "triangles"
  },
  "types-triangle": {
    "desc": "Understand the types of a triangle: equilateral, isosceles, scalene",
    "chap_id": "triangles"
  },
  "interior-exterior": {
    "desc": "Understand interior and exterior angles",
    "chap_id": "triangles"
  },
  "pythagorean_theorem": {
    "desc": "Understand and use the pythagorean theorem",
    "chap_id": "pythagorean_theorem"
  },
  "right_triangle": {
    "desc": "Identify a right triangle",
    "chap_id": "pythagorean_theorem"
  },
  "hypotenuse": {
    "desc": "Identify the hypotenuse of a triangle",
    "chap_id": "pythagorean_theorem"
  },
  "distance_formula": {
    "desc": "Understand the basics of the distance formula using the hypotenuse",
    "chap_id": "pythagorean_theorem"
  },
  "congruence": {
    "desc": "Understand the types of triangle congruence",
    "chap_id": "congruence"
  },
  "transformations": {
    "desc": "Understand the 3 types of transformations",
    "chap_id": "congruence"
  },
  "intro_vectors": {
    "desc": "Define the basics of vectors",
    "chap_id": "parallel_perpendicular"
  },
  "parallel": {
    "desc": "Understand parallel lines",
    "chap_id": "parallel_perpendicular"
  },
  "perpendicular": {
    "desc": "Understand perpendicular lines",
    "chap_id": "parallel_perpendicular"
  },
  "circles": {
    "desc": "Understand circles, their area, radius vs diameter, circumferences + area",
    "chap_id": "circles"
  },
  "circular_arc_length": {
    "desc": "Define arcs, arc length",
    "chap_id": "circles"
  },
  "sector": {
    "desc": "Define a sector in context of a circle",
    "chap_id": "circles"
  },
  "tangent": {
    "desc": "Define tangent in terms of a circle",
    "chap_id": "circles"
  },
  "math-function": {
    "desc": "Understand and define a function, and its domains/ranges. Differentiate from relations",
    "chap_id": "functions"
  },
  "math-variable": {
    "desc": "Understand and define a variable in terms of graphing and functions",
    "chap_id": "functions"
  },
  "math-graph": {
    "desc": "Understand and define a graph. Using desmos as a graphing simulator.",
    "chap_id": "functions"
  },
  "math-inverse_func": {
    "desc": "Understand the conversion between functions and their inverses.",
    "chap_id": "functions"
  },
  "volume-solids": {
    "desc": "Calculate the volume of different solids, including pyramids, cylinders, spheres, and unique shapes",
    "chap_id": "volume_solids"
  },
  "conic-sections": {
    "desc": "Understand and calculate, and graph conic sections",
    "chap_id": "conic_sections"
  },
  "circle-equation": {
    "desc": "Graph Circles",
    "chap_id": "conic_sections"
  },
  "ellipse-equation": {
    "desc": "Graph Ellipse",
    "chap_id": "conic_sections"
  },
  "hyperbola-equation": {
    "desc": "Graph Hyperbola",
    "chap_id": "conic_sections"
  },
  "parabola-equation": {
    "desc": "Graph Parabola",
    "chap_id": "conic_sections"
  },
  "manufacturing_methods": {
    "desc": "Understand various manufacturing methods and their benefits/drawbacks",
    "chap_id": "manufacturing"
  },
  "subtractive_manufacturing": {
    "desc": "Understand subtractive processes (ie milling, lathing)",
    "chap_id": "manufacturing"
  },
  "additive_manufacturing": {
    "desc": "Understand additive processes (ie 3d Printing)",
    "chap_id": "manufacturing"
  },
  "gravitational_acceleration": {
    "desc": "Understand acceleration due to gravity",
    "chap_id": "falling_bodies"
  },
  "python_basics": {
    "desc": "Start coding in python",
    "chap_id": "falling_bodies"
  },
  "intro_integration": {
    "desc": "Basics of integration using physics concepts",
    "chap_id": "falling_bodies"
  },
  "calc_velocity": {
    "desc": "Calculating velocity given acceleration and initial velocity",
    "chap_id": "falling_bodies"
  },
  "calc_accel": {
    "desc": "Calculating position given given a graph",
    "chap_id": "falling_bodies"
  },
  "air_resistance": {
    "desc": "Define air resistance (the video is a very good explanation)",
    "chap_id": "falling_bodies"
  },
  "free_fall": {
    "desc": "Understand free fall as a force concept",
    "chap_id": "falling_bodies"
  },
  "kinematic-equations": {
    "desc": "Use kinematic equations",
    "chap_id": "kinematics"
  },
  "distance_displacement": {
    "desc": "Understand the distance between distance vs displacement",
    "chap_id": "kinematics"
  },
  "projectile_motion": {
    "desc": "Understand projectile motion and independence of motion",
    "chap_id": "projectiles"
  },
  "solving_quadratics": {
    "desc": "Understanding how to solve quadratic equations",
    "chap_id": "solving_quadratics"
  },
  "quadratic_formula": {
    "desc": "Apply the quadratic formula to find the roots of the equation",
    "chap_id": "solving_quadratics"
  },
  "factoring_quadratics": {
    "desc": "Be able to factor quadratics",
    "chap_id": "solving_quadratics"
  },
  "complex_numbers": {
    "desc": "Understand and define complex numbers",
    "chap_id": "complex_numbers"
  },
  "arith_sequences": {
    "desc": "Understand and define arithmetic sequences",
    "chap_id": "sequences"
  },
  "geo_sequences": {
    "desc": "Understand and define geometric sequences",
    "chap_id": "sequences"
  },
  "recursion_intro": {
    "desc": "Basics of recursion via sequences",
    "chap_id": "sequences"
  },
  "sequences_def": {
    "desc": "Basics of Sequences",
    "chap_id": "sequences"
  },
  "vectors": {
    "desc": "Understand a vector and its properties in depth",
    "chap_id": "vectors"
  },
  "vector_add_sub": {
    "desc": "Able to do vector addition and subtraction",
    "chap_id": "vectors"
  },
  "scalar_multiplication": {
    "desc": "Scalar multiplication with vectors",
    "chap_id": "vectors"
  },
  "vector_magnitude": {
    "desc": "Calculate Vector Magnitude",
    "chap_id": "vectors"
  },
  "unit_vector": {
    "desc": "Define a unit vector",
    "chap_id": "vectors"
  },
  "momentum": {
    "desc": "Define momentum",
    "chap_id": "momentum"
  },
  "consv_momentum": {
    "desc": "Understand collisions and conservation of momentum",
    "chap_id": "momentum"
  },
  "dot_product": {
    "desc": "Understand and multiply vectors using the dot product",
    "chap_id": "dot"
  },
  "boat_terminology": {
    "desc": "Define a boat's hull, port, deck, starboard,bow, stern, and methods of motion",
    "chap_id": "boats"
  },
  "center_of_mass": {
    "desc": "Understand Center of mass",
    "chap_id": "boats"
  },
  "rudder": {
    "desc": "Understand and define the use of a rudder",
    "chap_id": "boats"
  },
  "sails": {
    "desc": "Understand how sails work, attributes of the wind force and how wind pressure works",
    "chap_id": "sailing"
  },
  "drag": {
    "desc": "Define drag and thrust",
    "chap_id": "airplanes"
  },
  "lift": {
    "desc": "Define lift",
    "chap_id": "airplanes"
  },
  "pitch-yaw-roll": {
    "desc": "Define pitch yaw and roll as the 3 axes of rotation",
    "chap_id": "airplanes"
  },
  "gliders": {
    "desc": "Understand glider usage",
    "chap_id": "airplanes"
  },
  "airplanes": {
    "desc": "How airplanes fly basics",
    "chap_id": "airplanes"
  },
  "fbd": {
    "desc": "Be able to understand, interpret, and draw free body diagrams. Review all digital resources videos!",
    "chap_id": "free_body_diagrams"
  },
  "compound_interest": {
    "desc": "Understand interest and compound interest",
    "chap_id": "compound_interest"
  },
  "exponential_growth": {
    "desc": "Calculate exponential growth and understand exponents",
    "chap_id": "compound_interest"
  },
  "bar_chart": {
    "desc": "Be able to graph and interpret a bar chart",
    "chap_id": "intro_dataviz"
  },
  "line_graph": {
    "desc": "Be able to graph and interpret a line graph",
    "chap_id": "intro_dataviz"
  },
  "pie_chart": {
    "desc": "Be able to graph and interpret a pie chart",
    "chap_id": "intro_dataviz"
  },
  "scatterplot": {
    "desc": "Be able to graph and interpret a scatterplot",
    "chap_id": "intro_dataviz"
  },
  "dataviz": {
    "desc": "Be able to understand graphs and data distributions",
    "chap_id": "intro_dataviz"
  },
  "atmos": {
    "desc": "Atmospheric pressure and altitude",
    "chap_id": "atmopressure"
  },
  "siphon": {
    "desc": "Understand how a siphon works, and how it works in a toilet",
    "chap_id": "atmopressure"
  },
  "exponents": {
    "desc": "Understand exponents",
    "chap_id": "exponents_review"
  },
  "exponent_properties": {
    "desc": "Understand exponent properties",
    "chap_id": "exponents_review"
  },
  "fractional_exponents": {
    "desc": "Understand fractional exponents",
    "chap_id": "exponents_review"
  },
  "exponential_decay": {
    "desc": "Understand and calculate exponential decay",
    "chap_id": "exponential_decay"
  },
  "half-life": {
    "desc": "Understand the concept of a half life",
    "chap_id": "exponential_decay"
  },
  "logarithms": {
    "desc": "Understand how to use logarithms",
    "chap_id": "logs"
  },
  "log_properties": {
    "desc": "Understand how to use logarithm properties",
    "chap_id": "logs"
  },
  "log_natural": {
    "desc": "Understand natural logs",
    "chap_id": "logs"
  },
  "sine": {
    "desc": "Introduction to the sine function and its graph",
    "chap_id": "trig_functions"
  },
  "cosine": {
    "desc": "Introduction to the cosine function and its graph",
    "chap_id": "trig_functions"
  },
  "trig_derivatives": {
    "desc": "Understand how to derive and use trig derivative functions, specifically with sin and cosine",
    "chap_id": "trig_functions"
  },
  "trig_functions": {
    "desc": "Understand the relationships with all of the trig functions",
    "chap_id": "trig_functions"
  },
  "trig_integrals": {
    "desc": "Understand the area under the curve as a trig integral, and integrate the trig functions",
    "chap_id": "trig_functions"
  },
  "inverse_trig": {
    "desc": "Understand and calculate all inverse trig functions",
    "chap_id": "inv_trig_functions"
  },
  "inv_trig_derivatives": {
    "desc": "Know the inverse trig derivatives",
    "chap_id": "inv_trig_functions"
  },
  "sum_diff_formulas": {
    "desc": "Understand use of sum and difference formulas",
    "chap_id": "trig_identities"
  },
  "double_half_angle_ids": {
    "desc": "Understand use of double angle and half angle identities",
    "chap_id": "trig_identities"
  },
  "unit circle": {
    "desc": "Understand the unit circle, how to locate different coordinates on it, and how to find side length values on it",
    "chap_id": "trig_identities"
  },
  "ac": {
    "desc": "Definition of Alternating Current",
    "chap_id": "ac"
  },
  "ac_transformer": {
    "desc": "Use of Transformer to Change Voltage of AC",
    "chap_id": "ac"
  },
  "decint-rep": {
    "desc": "Understand the base-10 hindu-arabic representation of numbers",
    "chap_id": "hexbinary"
  },
  "octal-rep": {
    "desc": "Understand the base-8 representation of the natural numbers",
    "chap_id": "hexbinary"
  },
  "hex-rep": {
    "desc": "Understand the base-16 representation of the natural numbers",
    "chap_id": "hexbinary"
  },
  "binary-rep": {
    "desc": "Understand the base-2 representation of the natural numbers",
    "chap_id": "hexbinary"
  },
  "gas-temp": {
    "desc": "How the temperature of a gas relates to the speed of the molecules",
    "chap_id": "gas"
  },
  "abs-zero": {
    "desc": "Absolute zero",
    "chap_id": "gas"
  },
  "ideal-gas-law": {
    "desc": "The Ideal Gas Law",
    "chap_id": "gas"
  }
}